{"data":{"search":[{"familyStylesByLicense":{"free":[],"pro":[{"family":"classic","style":"light"},{"family":"classic","style":"regular"},{"family":"classic","style":"solid"},{"family":"classic","style":"thin"},{"family":"duotone","style":"light"},{"family":"duotone","style":"regular"},{"family":"duotone","style":"solid"},{"family":"duotone","style":"thin"},{"family":"sharp","style":"light"},{"family":"sharp","style":"regular"},{"family":"sharp","style":"solid"},{"family":"sharp","style":"thin"},{"family":"sharp-duotone","style":"light"},{"family":"sharp-duotone","style":"regular"},{"family":"sharp-duotone","style":"solid"},{"family":"sharp-duotone","style":"thin"}]},"id":"coffee-pot","label":"Coffee Pot"},{"familyStylesByLicense":{"free":[],"pro":[{"family":"classic","style":"light"},{"family":"classic","style":"regular"},{"family":"classic","style":"solid"},{"family":"classic","style":"thin"},{"family":"duotone","style":"light"},{"family":"duotone","style":"regular"},{"family":"duotone","style":"solid"},{"family":"duotone","style":"thin"},{"family":"sharp","style":"light"},{"family":"sharp","style":"regular"},{"family":"sharp","style":"solid"},{"family":"sharp","style":"thin"},{"family":"sharp-duotone","style":"light"},{"family":"sharp-duotone","style":"regular"},{"family":"sharp-duotone","style":"solid"},{"family":"sharp-duotone","style":"thin"}]},"id":"coffee-beans","label":"Coffee Beans"},{"familyStylesByLicense":{"free":[],"pro":[{"family":"classic","style":"light"},{"family":"classic","style":"regular"},{"family":"classic","style":"solid"},{"family":"classic","style":"thin"},{"family":"duotone","style":"light"},{"family":"duotone","style":"regular"},{"family":"duotone","style":"solid"},{"family":"duotone","style":"thin"},{"family":"sharp","style":"light"},{"family":"sharp","style":"regular"},{"family":"sharp","style":"solid"},{"family":"sharp","style":"thin"},{"family":"sharp-duotone","style":"light"},{"family":"sharp-duotone","style":"regular"},{"family":"sharp-duotone","style":"solid"},{"family":"sharp-duotone","style":"thin"}]},"id":"coffee-bean","label":"Coffee Bean"},{"familyStylesByLicense":{"free":[],"pro":[{"family":"classic","style":"light"},{"family":"classic","style":"regular"},{"family":"classic","style":"solid"},{"family":"classic","style":"thin"},{"family":"duotone","style":"light"},{"family":"duotone","style":"regular"},{"family":"duotone","style":"solid"},{"family":"duotone","style":"thin"},{"family":"sharp","style":"light"},{"family":"sharp","style":"regular"},{"family":"sharp","style":"solid"},{"family":"sharp","style":"thin"},{"family":"sharp-duotone","style":"light"},{"family":"sharp-duotone","style":"regular"},{"family":"sharp-duotone","style":"solid"},{"family":"sharp-duotone","style":"thin"}]},"id":"mug","label":"Mug"},{"familyStylesByLicense":{"free":[],"pro":[{"family":"classic","style":"light"},{"family":"classic","style":"regular"},{"family":"classic","style":"solid"},{"family":"classic","style":"thin"},{"family":"duotone","style":"light"},{"family":"duotone","style":"regular"},{"family":"duotone","style":"solid"},{"family":"duotone","style":"thin"},{"family":"sharp","style":"light"},{"family":"sharp","style":"regular"},{"family":"sharp","style":"solid"},{"family":"sharp","style":"thin"},{"family":"sharp-duotone","style":"light"},{"family":"sharp-duotone","style":"regular"},{"family":"sharp-duotone","style":"solid"},{"family":"sharp-duotone","style":"thin"}]},"id":"mug-marshmallows","label":"Mug Marshmallows"},{"familyStylesByLicense":{"free":[{"family":"classic","style":"solid"}],"pro":[{"family":"chisel","style":"regular"},{"family":"classic","style":"light"},{"family":"classic","style":"regular"},{"family":"classic","style":"solid"},{"family":"classic","style":"thin"},{"family":"duotone","style":"light"},{"family":"duotone","style":"regular"},{"family":"duotone","style":"solid"},{"family":"duotone","style":"thin"},{"family":"etch","style":"solid"},{"family":"jelly","style":"regular"},{"family":"jelly-duo","style":"regular"},{"family":"jelly-fill","style":"regular"},{"family":"notdog","style":"solid"},{"family":"notdog-duo","style":"solid"},{"family":"sharp","style":"light"},{"family":"sharp","style":"regular"},{"family":"sharp","style":"solid"},{"family":"sharp","style":"thin"},{"family":"sharp-duotone","style":"light"},{"family":"sharp-duotone","style":"regular"},{"family":"sharp-duotone","style":"solid"},{"family":"sharp-duotone","style":"thin"},{"family":"slab","style":"regular"},{"family":"slab-press","style":"regular"},{"family":"thumbprint","style":"light"},{"family":"whiteboard","style":"semibold"}]},"id":"mug-hot","label":"Mug Hot"},{"familyStylesByLicense":{"free":[{"family":"classic","style":"solid"}],"pro":[{"family":"classic","style":"light"},{"family":"classic","style":"regular"},{"family":"classic","style":"solid"},{"family":"classic","style":"thin"},{"family":"duotone","style":"light"},{"family":"duotone","style":"regular"},{"family":"duotone","style":"solid"},{"family":"duotone","style":"thin"},{"family":"sharp","style":"light"},{"family":"sharp","style":"regular"},{"family":"sharp","style":"solid"},{"family":"sharp","style":"thin"},{"family":"sharp-duotone","style":"light"},{"family":"sharp-duotone","style":"regular"},{"family":"sharp-duotone","style":"solid"},{"family":"sharp-duotone","style":"thin"},{"family":"whiteboard","style":"semibold"}]},"id":"mug-saucer","label":"Mug Saucer"},{"familyStylesByLicense":{"free":[],"pro":[{"family":"classic","style":"light"},{"family":"classic","style":"regular"},{"family":"classic","style":"solid"},{"family":"classic","style":"thin"},{"family":"duotone","style":"light"},{"family":"duotone","style":"regular"},{"family":"duotone","style":"solid"},{"family":"duotone","style":"thin"},{"family":"sharp","style":"light"},{"family":"sharp","style":"regular"},{"family":"sharp","style":"solid"},{"family":"sharp","style":"thin"},{"family":"sharp-duotone","style":"light"},{"family":"sharp-duotone","style":"regular"},{"family":"sharp-duotone","style":"solid"},{"family":"sharp-duotone","style":"thin"}]},"id":"cup-togo","label":"Cup Togo"}]}}
